[
  {
    "calledCandidate": null,
    "calledCandidates": [],
    "candidatesWithVotes": [
      {
        "elected": false,
        "estimatedVotes": {
          "estimatedVotesHigh": 3094254,
          "estimatedVotesLow": 2531661,
          "estimatedVotesMid": 2812954,
          "turnoutHigh": 90.8,
          "turnoutLow": 110.98,
          "turnoutMid": 99
        },
        "firstName": "Blake",
        "id": 15592,
        "lastName": "Huber",
        "partyName": "Independent",
        "votes": 0
      },
      {
        "elected": false,
        "estimatedVotes": {
          "estimatedVotesHigh": 3094254,
          "estimatedVotesLow": 2531661,
          "estimatedVotesMid": 2812954,
          "turnoutHigh": 90.8,
          "turnoutLow": 110.98,
          "turnoutMid": 99
        },
        "firstName": "Randall",
        "id": 84941,
        "lastName": "Terry",
        "partyName": "Constitution",
        "votes": 0
      },
      {
        "elected": false,
        "estimatedVotes": {
          "estimatedVotesHigh": 3094254,
          "estimatedVotesLow": 2531661,
          "estimatedVotesMid": 2812954,
          "turnoutHigh": 90.8,
          "turnoutLow": 110.98,
          "turnoutMid": 99
        },
        "firstName": "Kamala",
        "id": 988,
        "lastName": "Harris",
        "partyName": "Democratic",
        "votes": 1476672
      },
      {
        "elected": false,
        "estimatedVotes": {
          "estimatedVotesHigh": 3094254,
          "estimatedVotesLow": 2531661,
          "estimatedVotesMid": 2812954,
          "turnoutHigh": 90.8,
          "turnoutLow": 110.98,
          "turnoutMid": 99
        },
        "firstName": "Jill",
        "id": 353,
        "lastName": "Stein",
        "partyName": "Green",
        "votes": 52667
      },
      {
        "elected": false,
        "estimatedVotes": {
          "estimatedVotesHigh": 3094254,
          "estimatedVotesLow": 2531661,
          "estimatedVotesMid": 2812954,
          "turnoutHigh": 90.8,
          "turnoutLow": 110.98,
          "turnoutMid": 99
        },
        "firstName": "Robert F.",
        "id": 69575,
        "lastName": "Kennedy Jr.",
        "partyName": "Independent",
        "votes": 0
      },
      {
        "elected": false,
        "estimatedVotes": {
          "estimatedVotesHigh": 3094254,
          "estimatedVotesLow": 2531661,
          "estimatedVotesMid": 2812954,
          "turnoutHigh": 90.8,
          "turnoutLow": 110.98,
          "turnoutMid": 99
        },
        "firstName": "Cornel",
        "id": 84938,
        "lastName": "West",
        "partyName": "Independent",
        "votes": 53031
      },
      {
        "elected": false,
        "estimatedVotes": {
          "estimatedVotesHigh": 3094254,
          "estimatedVotesLow": 2531661,
          "estimatedVotesMid": 2812954,
          "turnoutHigh": 90.8,
          "turnoutLow": 110.98,
          "turnoutMid": 99
        },
        "firstName": "Chase",
        "id": 14810,
        "lastName": "Oliver",
        "partyName": "Libertarian",
        "votes": 53736
      },
      {
        "elected": false,
        "estimatedVotes": {
          "estimatedVotesHigh": 3094254,
          "estimatedVotesLow": 2531661,
          "estimatedVotesMid": 2812954,
          "turnoutHigh": 90.8,
          "turnoutLow": 110.98,
          "turnoutMid": 99
        },
        "firstName": "Donald J.",
        "id": 5,
        "lastName": "Trump",
        "partyName": "Republican",
        "votes": 1173493
      }
    ],
    "district": "",
    "electionType": {
      "electionType": "General Election",
      "electionTypeId": "1"
    },
    "hasCalledCandidate": false,
    "lastUpdated": "2024-10-28T07:24:22.520Z",
    "office": {
      "officeId": "1",
      "officeName": "President",
      "officeTypeId": "1"
    },
    "partyName": null,
    "raceDate": "2024-11-05",
    "state": "CO",
    "stateName": "Colorado",
    "totalVotes": 2809599,
    "year": 2024
  },
  {
    "calledCandidate": null,
    "calledCandidates": [],
    "candidatesWithVotes": [
      {
        "elected": false,
        "estimatedVotes": {
          "estimatedVotesHigh": 341119,
          "estimatedVotesLow": 279097,
          "estimatedVotesMid": 310108,
          "turnoutHigh": 91.61,
          "turnoutLow": 111.97,
          "turnoutMid": 99
        },
        "firstName": "Critter",
        "id": 48171,
        "lastName": "Milton",
        "partyName": "Unity Party of Colorado",
        "votes": 5629
      },
      {
        "elected": false,
        "estimatedVotes": {
          "estimatedVotesHigh": 341119,
          "estimatedVotesLow": 279097,
          "estimatedVotesMid": 310108,
          "turnoutHigh": 91.61,
          "turnoutLow": 111.97,
          "turnoutMid": 99
        },
        "firstName": "Valdamar",
        "id": 76770,
        "lastName": "Archuleta",
        "partyName": "Republican",
        "votes": 56452
      },
      {
        "elected": false,
        "estimatedVotes": {
          "estimatedVotesHigh": 341119,
          "estimatedVotesLow": 279097,
          "estimatedVotesMid": 310108,
          "turnoutHigh": 91.61,
          "turnoutLow": 111.97,
          "turnoutMid": 99
        },
        "firstName": "Daniel",
        "id": 102115,
        "lastName": "Lutz",
        "partyName": "Approval Voting Party",
        "votes": 6132
      },
      {
        "elected": false,
        "estimatedVotes": {
          "estimatedVotesHigh": 341119,
          "estimatedVotesLow": 279097,
          "estimatedVotesMid": 310108,
          "turnoutHigh": 91.61,
          "turnoutLow": 111.97,
          "turnoutMid": 99
        },
        "firstName": "Diana",
        "id": 326,
        "lastName": "DeGette",
        "partyName": "Democratic",
        "votes": 244288
      }
    ],
    "district": "1",
    "electionType": {
      "electionType": "General Election",
      "electionTypeId": "1"
    },
    "hasCalledCandidate": false,
    "lastUpdated": "2024-10-28T07:24:51.705Z",
    "office": {
      "officeId": "3",
      "officeName": "US House",
      "officeTypeId": "2"
    },
    "partyName": null,
    "raceDate": "2024-11-05",
    "state": "CO",
    "stateName": "Colorado",
    "totalVotes": 312501,
    "year": 2024
  },
  {
    "calledCandidate": null,
    "calledCandidates": [],
    "candidatesWithVotes": [
      {
        "elected": false,
        "estimatedVotes": {
          "estimatedVotesHigh": 408300,
          "estimatedVotesLow": 334066,
          "estimatedVotesMid": 371183,
          "turnoutHigh": 90.92,
          "turnoutLow": 111.12,
          "turnoutMid": 99
        },
        "firstName": "Marshall",
        "id": 24680,
        "lastName": "Dawson",
        "partyName": "Republican",
        "votes": 102198
      },
      {
        "elected": false,
        "estimatedVotes": {
          "estimatedVotesHigh": 408300,
          "estimatedVotesLow": 334066,
          "estimatedVotesMid": 371183,
          "turnoutHigh": 90.92,
          "turnoutLow": 111.12,
          "turnoutMid": 99
        },
        "firstName": "Jan",
        "id": 48237,
        "lastName": "Kok",
        "partyName": "Approval Voting Party",
        "votes": 6627
      },
      {
        "elected": false,
        "estimatedVotes": {
          "estimatedVotesHigh": 408300,
          "estimatedVotesLow": 334066,
          "estimatedVotesMid": 371183,
          "turnoutHigh": 90.92,
          "turnoutLow": 111.12,
          "turnoutMid": 99
        },
        "firstName": "Cynthia",
        "id": 102118,
        "lastName": "Sirianni",
        "partyName": "Unity Party of Colorado",
        "votes": 7177
      },
      {
        "elected": false,
        "estimatedVotes": {
          "estimatedVotesHigh": 408300,
          "estimatedVotesLow": 334066,
          "estimatedVotesMid": 371183,
          "turnoutHigh": 90.92,
          "turnoutLow": 111.12,
          "turnoutMid": 99
        },
        "firstName": "Gaylon",
        "id": 1903,
        "lastName": "Kent",
        "partyName": "Libertarian",
        "votes": 6925
      },
      {
        "elected": false,
        "estimatedVotes": {
          "estimatedVotesHigh": 408300,
          "estimatedVotesLow": 334066,
          "estimatedVotesMid": 371183,
          "turnoutHigh": 90.92,
          "turnoutLow": 111.12,
          "turnoutMid": 99
        },
        "firstName": "Joe",
        "id": 10008,
        "lastName": "Neguse",
        "partyName": "Democratic",
        "votes": 248293
      }
    ],
    "district": "2",
    "electionType": {
      "electionType": "General Election",
      "electionTypeId": "1"
    },
    "hasCalledCandidate": false,
    "lastUpdated": "2024-10-28T07:24:51.705Z",
    "office": {
      "officeId": "3",
      "officeName": "US House",
      "officeTypeId": "2"
    },
    "partyName": null,
    "raceDate": "2024-11-05",
    "state": "CO",
    "stateName": "Colorado",
    "totalVotes": 371220,
    "year": 2024
  },
  {
    "calledCandidate": null,
    "calledCandidates": [],
    "candidatesWithVotes": [
      {
        "elected": false,
        "estimatedVotes": {
          "estimatedVotesHigh": 402593,
          "estimatedVotesLow": 329394,
          "estimatedVotesMid": 365993,
          "turnoutHigh": 90.91,
          "turnoutLow": 111.11,
          "turnoutMid": 99
        },
        "firstName": "Jeff",
        "id": 76774,
        "lastName": "Hurd",
        "partyName": "Republican",
        "votes": 189061
      },
      {
        "elected": false,
        "estimatedVotes": {
          "estimatedVotesHigh": 402593,
          "estimatedVotesLow": 329394,
          "estimatedVotesMid": 365993,
          "turnoutHigh": 90.91,
          "turnoutLow": 111.11,
          "turnoutMid": 99
        },
        "firstName": "Adam",
        "id": 24671,
        "lastName": "Frisch",
        "partyName": "Democratic",
        "votes": 162887
      },
      {
        "elected": false,
        "estimatedVotes": {
          "estimatedVotesHigh": 402593,
          "estimatedVotesLow": 329394,
          "estimatedVotesMid": 365993,
          "turnoutHigh": 90.91,
          "turnoutLow": 111.11,
          "turnoutMid": 99
        },
        "firstName": "Adam",
        "id": 102120,
        "lastName": "Withrow",
        "partyName": "Unity Party of Colorado",
        "votes": 7007
      },
      {
        "elected": false,
        "estimatedVotes": {
          "estimatedVotesHigh": 402593,
          "estimatedVotesLow": 329394,
          "estimatedVotesMid": 365993,
          "turnoutHigh": 90.91,
          "turnoutLow": 111.11,
          "turnoutMid": 99
        },
        "firstName": "James",
        "id": 102119,
        "lastName": "Wiley",
        "partyName": "Libertarian",
        "votes": 7048
      }
    ],
    "district": "3",
    "electionType": {
      "electionType": "General Election",
      "electionTypeId": "1"
    },
    "hasCalledCandidate": false,
    "lastUpdated": "2024-10-28T07:24:51.705Z",
    "office": {
      "officeId": "3",
      "officeName": "US House",
      "officeTypeId": "2"
    },
    "partyName": null,
    "raceDate": "2024-11-05",
    "state": "CO",
    "stateName": "Colorado",
    "totalVotes": 366003,
    "year": 2024
  },
  {
    "calledCandidate": null,
    "calledCandidates": [],
    "candidatesWithVotes": [
      {
        "elected": false,
        "estimatedVotes": {
          "estimatedVotesHigh": 447186,
          "estimatedVotesLow": 365876,
          "estimatedVotesMid": 406529,
          "turnoutHigh": 90.92,
          "turnoutLow": 111.13,
          "turnoutMid": 99
        },
        "firstName": "Hannah",
        "id": 78626,
        "lastName": "Goodman",
        "partyName": "Libertarian",
        "votes": 7245
      },
      {
        "elected": false,
        "estimatedVotes": {
          "estimatedVotesHigh": 447186,
          "estimatedVotesLow": 365876,
          "estimatedVotesMid": 406529,
          "turnoutHigh": 90.92,
          "turnoutLow": 111.13,
          "turnoutMid": 99
        },
        "firstName": "Lauren",
        "id": 13808,
        "lastName": "Boebert",
        "partyName": "Republican",
        "votes": 227809
      },
      {
        "elected": false,
        "estimatedVotes": {
          "estimatedVotesHigh": 447186,
          "estimatedVotesLow": 365876,
          "estimatedVotesMid": 406529,
          "turnoutHigh": 90.92,
          "turnoutLow": 111.13,
          "turnoutMid": 99
        },
        "firstName": "Frank",
        "id": 44231,
        "lastName": "Atwood",
        "partyName": "Approval Voting Party",
        "votes": 7463
      },
      {
        "elected": false,
        "estimatedVotes": {
          "estimatedVotesHigh": 447186,
          "estimatedVotesLow": 365876,
          "estimatedVotesMid": 406529,
          "turnoutHigh": 90.92,
          "turnoutLow": 111.13,
          "turnoutMid": 99
        },
        "firstName": "Paul",
        "id": 47381,
        "lastName": "Fiorino",
        "partyName": "Unity Party of Colorado",
        "votes": 7496
      },
      {
        "elected": false,
        "estimatedVotes": {
          "estimatedVotesHigh": 447186,
          "estimatedVotesLow": 365876,
          "estimatedVotesMid": 406529,
          "turnoutHigh": 90.92,
          "turnoutLow": 111.13,
          "turnoutMid": 99
        },
        "firstName": "Trish",
        "id": 84985,
        "lastName": "Calvarese",
        "partyName": "Democratic",
        "votes": 156570
      }
    ],
    "district": "4",
    "electionType": {
      "electionType": "General Election",
      "electionTypeId": "1"
    },
    "hasCalledCandidate": false,
    "lastUpdated": "2024-10-28T07:24:51.705Z",
    "office": {
      "officeId": "3",
      "officeName": "US House",
      "officeTypeId": "2"
    },
    "partyName": null,
    "raceDate": "2024-11-05",
    "state": "CO",
    "stateName": "Colorado",
    "totalVotes": 406583,
    "year": 2024
  },
  {
    "calledCandidate": null,
    "calledCandidates": [],
    "candidatesWithVotes": [
      {
        "elected": false,
        "estimatedVotes": {
          "estimatedVotesHigh": 344614,
          "estimatedVotesLow": 281957,
          "estimatedVotesMid": 313285,
          "turnoutHigh": 90.91,
          "turnoutLow": 111.11,
          "turnoutMid": 99
        },
        "firstName": "Joseph",
        "id": 102123,
        "lastName": "Gaye",
        "partyName": "Independent",
        "votes": 6555
      },
      {
        "elected": false,
        "estimatedVotes": {
          "estimatedVotesHigh": 344614,
          "estimatedVotesLow": 281957,
          "estimatedVotesMid": 313285,
          "turnoutHigh": 90.91,
          "turnoutLow": 111.11,
          "turnoutMid": 99
        },
        "firstName": "Jeff",
        "id": 76781,
        "lastName": "Crank",
        "partyName": "Republican",
        "votes": 156305
      },
      {
        "elected": false,
        "estimatedVotes": {
          "estimatedVotesHigh": 344614,
          "estimatedVotesLow": 281957,
          "estimatedVotesMid": 313285,
          "turnoutHigh": 90.91,
          "turnoutLow": 111.11,
          "turnoutMid": 99
        },
        "firstName": "Michael",
        "id": 102122,
        "lastName": "Vance",
        "partyName": "Libertarian",
        "votes": 6311
      },
      {
        "elected": false,
        "estimatedVotes": {
          "estimatedVotesHigh": 344614,
          "estimatedVotesLow": 281957,
          "estimatedVotesMid": 313285,
          "turnoutHigh": 90.91,
          "turnoutLow": 111.11,
          "turnoutMid": 99
        },
        "firstName": "River",
        "id": 76779,
        "lastName": "Gassen",
        "partyName": "Democratic",
        "votes": 131708
      },
      {
        "elected": false,
        "estimatedVotes": {
          "estimatedVotesHigh": 344614,
          "estimatedVotesLow": 281957,
          "estimatedVotesMid": 313285,
          "turnoutHigh": 90.91,
          "turnoutLow": 111.11,
          "turnoutMid": 99
        },
        "firstName": "Christopher",
        "id": 44302,
        "lastName": "Mitchell",
        "partyName": "Constitution",
        "votes": 5697
      },
      {
        "elected": false,
        "estimatedVotes": {
          "estimatedVotesHigh": 344614,
          "estimatedVotesLow": 281957,
          "estimatedVotesMid": 313285,
          "turnoutHigh": 90.91,
          "turnoutLow": 111.11,
          "turnoutMid": 99
        },
        "firstName": "Christopher",
        "id": 102121,
        "lastName": "Sweat",
        "partyName": "Forward",
        "votes": 6708
      }
    ],
    "district": "5",
    "electionType": {
      "electionType": "General Election",
      "electionTypeId": "1"
    },
    "hasCalledCandidate": false,
    "lastUpdated": "2024-10-28T07:24:51.705Z",
    "office": {
      "officeId": "3",
      "officeName": "US House",
      "officeTypeId": "2"
    },
    "partyName": null,
    "raceDate": "2024-11-05",
    "state": "CO",
    "stateName": "Colorado",
    "totalVotes": 313284,
    "year": 2024
  },
  {
    "calledCandidate": null,
    "calledCandidates": [],
    "candidatesWithVotes": [
      {
        "elected": false,
        "estimatedVotes": {
          "estimatedVotesHigh": 366534,
          "estimatedVotesLow": 299890,
          "estimatedVotesMid": 333212,
          "turnoutHigh": 90.73,
          "turnoutLow": 110.9,
          "turnoutMid": 99
        },
        "firstName": "John",
        "id": 76782,
        "lastName": "Fabbricatore",
        "partyName": "Republican",
        "votes": 124209
      },
      {
        "elected": false,
        "estimatedVotes": {
          "estimatedVotesHigh": 366534,
          "estimatedVotesLow": 299890,
          "estimatedVotesMid": 333212,
          "turnoutHigh": 90.73,
          "turnoutLow": 110.9,
          "turnoutMid": 99
        },
        "firstName": "Jason",
        "id": 10052,
        "lastName": "Crow",
        "partyName": "Democratic",
        "votes": 195659
      },
      {
        "elected": false,
        "estimatedVotes": {
          "estimatedVotesHigh": 366534,
          "estimatedVotesLow": 299890,
          "estimatedVotesMid": 333212,
          "turnoutHigh": 90.73,
          "turnoutLow": 110.9,
          "turnoutMid": 99
        },
        "firstName": "Travis",
        "id": 102124,
        "lastName": "Nicks",
        "partyName": "Approval Voting Party",
        "votes": 6475
      },
      {
        "elected": false,
        "estimatedVotes": {
          "estimatedVotesHigh": 366534,
          "estimatedVotesLow": 299890,
          "estimatedVotesMid": 333212,
          "turnoutHigh": 90.73,
          "turnoutLow": 110.9,
          "turnoutMid": 99
        },
        "firstName": "John",
        "id": 44296,
        "lastName": "Kittleson",
        "partyName": "Libertarian",
        "votes": 6222
      }
    ],
    "district": "6",
    "electionType": {
      "electionType": "General Election",
      "electionTypeId": "1"
    },
    "hasCalledCandidate": false,
    "lastUpdated": "2024-10-28T07:24:51.705Z",
    "office": {
      "officeId": "3",
      "officeName": "US House",
      "officeTypeId": "2"
    },
    "partyName": null,
    "raceDate": "2024-11-05",
    "state": "CO",
    "stateName": "Colorado",
    "totalVotes": 332565,
    "year": 2024
  },
  {
    "calledCandidate": null,
    "calledCandidates": [],
    "candidatesWithVotes": [
      {
        "elected": false,
        "estimatedVotes": {
          "estimatedVotesHigh": 439614,
          "estimatedVotesLow": 359687,
          "estimatedVotesMid": 399650,
          "turnoutHigh": 91.12,
          "turnoutLow": 111.37,
          "turnoutMid": 99
        },
        "firstName": "Ron",
        "id": 102126,
        "lastName": "Tupa",
        "partyName": "Unity Party of Colorado",
        "votes": 7263
      },
      {
        "elected": false,
        "estimatedVotes": {
          "estimatedVotesHigh": 439614,
          "estimatedVotesLow": 359687,
          "estimatedVotesMid": 399650,
          "turnoutHigh": 91.12,
          "turnoutLow": 111.37,
          "turnoutMid": 99
        },
        "firstName": "Patrick",
        "id": 102125,
        "lastName": "Bohan",
        "partyName": "Libertarian",
        "votes": 7289
      },
      {
        "elected": false,
        "estimatedVotes": {
          "estimatedVotesHigh": 439614,
          "estimatedVotesLow": 359687,
          "estimatedVotesMid": 399650,
          "turnoutHigh": 91.12,
          "turnoutLow": 111.37,
          "turnoutMid": 99
        },
        "firstName": "Sergei",
        "id": 76783,
        "lastName": "Matveyuk",
        "partyName": "Republican",
        "votes": 166917
      },
      {
        "elected": false,
        "estimatedVotes": {
          "estimatedVotesHigh": 439614,
          "estimatedVotesLow": 359687,
          "estimatedVotesMid": 399650,
          "turnoutHigh": 91.12,
          "turnoutLow": 111.37,
          "turnoutMid": 99
        },
        "firstName": "Brittany",
        "id": 24677,
        "lastName": "Pettersen",
        "partyName": "Democratic",
        "votes": 219115
      }
    ],
    "district": "7",
    "electionType": {
      "electionType": "General Election",
      "electionTypeId": "1"
    },
    "hasCalledCandidate": false,
    "lastUpdated": "2024-10-28T07:24:51.705Z",
    "office": {
      "officeId": "3",
      "officeName": "US House",
      "officeTypeId": "2"
    },
    "partyName": null,
    "raceDate": "2024-11-05",
    "state": "CO",
    "stateName": "Colorado",
    "totalVotes": 400584,
    "year": 2024
  },
  {
    "calledCandidate": null,
    "calledCandidates": [],
    "candidatesWithVotes": [
      {
        "elected": false,
        "estimatedVotes": {
          "estimatedVotesHigh": 344179,
          "estimatedVotesLow": 281600,
          "estimatedVotesMid": 312889,
          "turnoutHigh": 90.91,
          "turnoutLow": 111.11,
          "turnoutMid": 99
        },
        "firstName": "Yadira",
        "id": 24678,
        "lastName": "Caraveo",
        "partyName": "Democratic",
        "votes": 160013
      },
      {
        "elected": false,
        "estimatedVotes": {
          "estimatedVotesHigh": 344179,
          "estimatedVotesLow": 281600,
          "estimatedVotesMid": 312889,
          "turnoutHigh": 90.91,
          "turnoutLow": 111.11,
          "turnoutMid": 99
        },
        "firstName": "Chris",
        "id": 102127,
        "lastName": "Baum",
        "partyName": "Approval Voting Party",
        "votes": 6381
      },
      {
        "elected": false,
        "estimatedVotes": {
          "estimatedVotesHigh": 344179,
          "estimatedVotesLow": 281600,
          "estimatedVotesMid": 312889,
          "turnoutHigh": 90.91,
          "turnoutLow": 111.11,
          "turnoutMid": 99
        },
        "firstName": "Gabe",
        "id": 24852,
        "lastName": "Evans",
        "partyName": "Republican",
        "votes": 140472
      },
      {
        "elected": false,
        "estimatedVotes": {
          "estimatedVotesHigh": 344179,
          "estimatedVotesLow": 281600,
          "estimatedVotesMid": 312889,
          "turnoutHigh": 90.91,
          "turnoutLow": 111.11,
          "turnoutMid": 99
        },
        "firstName": "Susan",
        "id": 102128,
        "lastName": "Hall",
        "partyName": "Unity Party of Colorado",
        "votes": 6024
      }
    ],
    "district": "8",
    "electionType": {
      "electionType": "General Election",
      "electionTypeId": "1"
    },
    "hasCalledCandidate": false,
    "lastUpdated": "2024-10-28T07:24:51.705Z",
    "office": {
      "officeId": "3",
      "officeName": "US House",
      "officeTypeId": "2"
    },
    "partyName": null,
    "raceDate": "2024-11-05",
    "state": "CO",
    "stateName": "Colorado",
    "totalVotes": 312890,
    "year": 2024
  }
]
